brite_etl/.DS_Store
brite_etl/__init__.py
brite_etl/__main__.py
brite_etl/_globals.py
brite_etl/decorators.py
brite_etl/exceptions.py
brite_etl/helpers.py
brite_etl/abstracts/.DS_Store
brite_etl/abstracts/__init__.py
brite_etl/abstracts/frame.py
brite_etl/abstracts/frame_data_source.py
brite_etl/cli/.DS_Store
brite_etl/cli/__init__.py
brite_etl/cli/main.py
brite_etl/cli/generate/.DS_Store
brite_etl/cli/generate/__init__.py
brite_etl/cli/generate/frame.py
brite_etl/cli/generate/main.py
brite_etl/cli/generate/templates/frame_template.py
brite_etl/core/__init__.py
brite_etl/core/computations/__init__.py
brite_etl/core/computations/get_item_transactions.py
brite_etl/core/io/__init__.py
brite_etl/core/io/export_excel.py
brite_etl/core/io/frame_sources.py
brite_etl/core/io/import_report.py
brite_etl/core/operations/__init__.py
brite_etl/core/operations/hash_cols.py
brite_etl/frames/.DS_Store
brite_etl/frames/__init__.py
brite_etl/frames/account_history.py
brite_etl/frames/additional_interests.py
brite_etl/frames/addresses.py
brite_etl/frames/agencies.py
brite_etl/frames/builder_obj.py
brite_etl/frames/builder_obj_parsed.py
brite_etl/frames/catastrophes.py
brite_etl/frames/claim_items.py
brite_etl/frames/claims.py
brite_etl/frames/claims_changes.py
brite_etl/frames/claims_contacts.py
brite_etl/frames/claims_payments.py
brite_etl/frames/claims_payments_item_amounts.py
brite_etl/frames/claims_perils.py
brite_etl/frames/claims_recoveries.py
brite_etl/frames/commission_accounting.py
brite_etl/frames/commission_payments.py
brite_etl/frames/committed_revisions.py
brite_etl/frames/committed_revisions_all.py
brite_etl/frames/credit_reports.py
brite_etl/frames/custom_data.py
brite_etl/frames/emails.py
brite_etl/frames/files.py
brite_etl/frames/inactive_claims.py
brite_etl/frames/inspectors.py
brite_etl/frames/item_questions.py
brite_etl/frames/lines.py
brite_etl/frames/losses_incurred.py
brite_etl-0.1.1.dist-info/DESCRIPTION.rst
brite_etl-0.1.1.dist-info/METADATA
brite_etl-0.1.1.dist-info/RECORD
brite_etl-0.1.1.dist-info/WHEEL
brite_etl-0.1.1.dist-info/entry_points.txt
brite_etl-0.1.1.dist-info/metadata.json
brite_etl-0.1.1.dist-info/top_level.txt
