Metadata-Version: 2.0
Name: brite-etl
Version: 0.1.1
Summary: A python package for working with the BriteCore ETL.
Home-page: https://github.com/haydenbbickerton/brite_etl
Author: Hayden Bickerton
Author-email: hayden@britecore.com
License: UNKNOWN
Keywords: BriteCore,brite_etl
Platform: UNKNOWN
Classifier: Development Status :: 3 - Alpha
Classifier: Intended Audience :: Developers
Classifier: Intended Audience :: Financial and Insurance Industry
Classifier: Natural Language :: English
Classifier: Operating System :: Unix
Classifier: Operating System :: POSIX
Classifier: Operating System :: Microsoft :: Windows
Classifier: Operating System :: MacOS :: MacOS X
Classifier: Programming Language :: Python
Classifier: Programming Language :: Python :: 2.7
Classifier: Programming Language :: Python :: 3.5
Classifier: Topic :: Utilities
Requires-Dist: click
Requires-Dist: coloredlogs
Requires-Dist: mock
Requires-Dist: pandas
Requires-Dist: pydash
Requires-Dist: typedecorator
Requires-Dist: xlwings
